README.md
setup.py
gruut_lang_it/VERSION
gruut_lang_it/__init__.py
gruut_lang_it/lexicon.db
gruut_lang_it.egg-info/PKG-INFO
gruut_lang_it.egg-info/SOURCES.txt
gruut_lang_it.egg-info/dependency_links.txt
gruut_lang_it.egg-info/top_level.txt
gruut_lang_it/espeak/lexicon.db
gruut_lang_it/espeak/g2p/model.crf
gruut_lang_it/g2p/model.crf